CODE_OF_CONDUCT.md
CONTRIBUTING.md
LICENSE
MANIFEST.in
README.md
README.rst
setup.py
vapeplot/__init__.py
vapeplot/vapeplot.py
vapeplot.egg-info/PKG-INFO
vapeplot.egg-info/SOURCES.txt
vapeplot.egg-info/dependency_links.txt
vapeplot.egg-info/requires.txt
vapeplot.egg-info/top_level.txt