Metadata-Version: 1.1
Name: vapeplot
Version: 0.0.8
Summary: matplotlib extension for vaporwave aesthetics
Home-page: https://github.com/dantaki/vapeplot/
Author: Danny Antaki
Author-email: dantaki@ucsd.edu
License: GPLv2
Keywords: vaporwave matplotlib
Platform: UNKNOWN
Classifier: Development Status :: 3 - Alpha
Classifier: License :: OSI Approved :: GNU General Public License v2 (GPLv2)
Classifier: Topic :: Multimedia :: Graphics
